ai_md_scaffold/__init__.py
ai_md_scaffold/__main__.py
ai_md_scaffold/generator.py
ai_md_scaffold/parser.py
ai_md_scaffold-1.2.0.dist-info/licenses/LICENSE
ai_md_scaffold-1.2.0.dist-info/METADATA
ai_md_scaffold-1.2.0.dist-info/WHEEL
ai_md_scaffold-1.2.0.dist-info/entry_points.txt
ai_md_scaffold-1.2.0.dist-info/top_level.txt
ai_md_scaffold-1.2.0.dist-info/RECORD
