Metadata-Version: 2.4
Name: ai-md-scaffold
Version: 1.2.0
Summary: Turn AI-generated Markdown into real project files
Author: Falah
License: MIT
Requires-Python: >=3.8
License-File: LICENSE
Dynamic: license-file
